mw_python_sdk/__init__.py
mw_python_sdk/api.py
mw_python_sdk/common.py
mw_python_sdk/dataset.py
mw_python_sdk/main.py
mw_sdk_python-0.0.2.dist-info/METADATA
mw_sdk_python-0.0.2.dist-info/WHEEL
mw_sdk_python-0.0.2.dist-info/top_level.txt
mw_sdk_python-0.0.2.dist-info/RECORD
