Metadata-Version: 2.1
Name: mw-sdk-python
Version: 0.0.2
Summary: ModelWhale SDK
Author-email: Peng Gao <mike@heywhale.com>
Project-URL: Homepage, https://github.com/Kesci/mw-python-sdk
Project-URL: Issues, https://github.com/Kesci/mw-python-sdk/issues
Classifier: Programming Language :: Python :: 3
Classifier: License :: OSI Approved :: MIT License
Classifier: Operating System :: OS Independent
Requires-Python: >=3.8
Requires-Dist: PyJWT
Requires-Dist: requests
Requires-Dist: boto3
Requires-Dist: tqdm
